{"style_bNavID":"","data_pageName":"首页","style_bgPic":"1455695617821_977917.jpg","style_bNavType":2001,"style_tFlag":0,"style_bgType":2,"style_bgColor":"1F497D","sys_pageID":"b93bcd73-b249-439f-a588-3a17e03a38ba","data_password":"","style_tNavID":"","item":[{"style_textSize":20,"sys_z":0,"data_text":"官方微博","style_bgPic":"","sys_moduleType":1,"style_textAlign":1,"style_bgType":1,"sys_w":129,"nPageType":0,"sys_y":393,"sys_x":13,"style_textBold":1,"style_bgColor":"95B3D7","sys_h":38,"style_textColor":"FFFFFF","nPageId":"d4299fec-fbe8-4c25-bece-f3a8d546105e","nFlag":1,"style_bgAlpha":22},{"style_textSize":20,"sys_z":1,"data_text":"崇才微博","style_bgPic":"","sys_moduleType":1,"style_textAlign":1,"style_bgType":1,"sys_w":129,"nPageType":0,"sys_y":393,"sys_x":162,"style_textBold":1,"style_bgColor":"95B3D7","sys_h":38,"style_textColor":"FFFFFF","nPageId":"cbcfee6f-efa3-43fc-be2e-509608fa819a","nFlag":1,"style_bgAlpha":22},{"style_textSize":20,"sys_z":2,"data_text":"最新信息","style_bgPic":"","sys_moduleType":1,"style_textAlign":1,"style_bgType":1,"sys_w":129,"nPageType":0,"sys_y":334,"sys_x":13,"style_textBold":1,"style_bgColor":"95B3D7","sys_h":38,"style_textColor":"FFFFFF","nPageId":"3993f1a4-4d28-4649-95e1-0f287c831dd2","nFlag":1,"style_bgAlpha":22},{"style_textSize":20,"sys_z":3,"data_text":"个人中心","style_bgPic":"","sys_moduleType":1,"style_textAlign":1,"style_bgType":1,"sys_w":129,"nPageType":0,"sys_y":334,"sys_x":162,"style_textBold":1,"style_bgColor":"95B3D7","sys_h":38,"style_textColor":"FFFFFF","nPageId":"9127ed51-c126-4044-9035-bac9fddf4ba4","nFlag":1,"style_bgAlpha":22},{"style_textSize":10,"sys_z":4,"data_text":"新闻版","style_bgPic":"","sys_moduleType":1,"style_textAlign":1,"style_bgType":1,"sys_w":129,"nPageType":0,"sys_y":441,"sys_x":88,"style_textBold":1,"style_bgColor":"95B3D7","sys_h":34,"style_textColor":"FFFFFF","nPageId":"e2f161c0-842a-4331-83ca-757301cc85e8","nFlag":1,"style_bgAlpha":22}],"style_tNavType":1001,"style_bFlag":0,"style_bgAlpha":100}